thothai_cli_core/__init__.py
thothai_cli_core/docker_ops.py
thothai_cli_core-1.0.1.dist-info/METADATA
thothai_cli_core-1.0.1.dist-info/WHEEL
thothai_cli_core-1.0.1.dist-info/licenses/LICENSE.md
thothai_cli_core-1.0.1.dist-info/RECORD
