Metadata-Version: 2.4
Name: thothai-cli-core
Version: 1.0.1
Summary: Core logic for ThothAI CLIs - Docker and Data Management
License: Apache-2.0
License-File: LICENSE.md
Requires-Python: >=3.9
Requires-Dist: click>=8.0
Requires-Dist: pyyaml>=6.0
Requires-Dist: rich>=13.0
